os_api_cache/__init__.py
os_api_cache/base_cache.py
os_api_cache/os_cache.py
os_api_cache/redis_cache.py
os_api_cache-0.0.7.dist-info/DESCRIPTION.rst
os_api_cache-0.0.7.dist-info/METADATA
os_api_cache-0.0.7.dist-info/RECORD
os_api_cache-0.0.7.dist-info/WHEEL
os_api_cache-0.0.7.dist-info/metadata.json
os_api_cache-0.0.7.dist-info/top_level.txt
