Metadata-Version: 2.0
Name: os-api-cache
Version: 0.0.7
Summary: Manage a cache for OpenSpending API
Home-page: https://github.com/openspending/os-api-cache
Author: Open Knowledge International
Author-email: info@okfn.org
License: MIT
Keywords: fdp fiscal data api openspending cache
Platform: UNKNOWN
Classifier: Development Status :: 4 - Beta
Classifier: Intended Audience :: Developers
Classifier: Intended Audience :: Information Technology
Classifier: Topic :: Utilities
Classifier: License :: OSI Approved :: MIT License
Classifier: Programming Language :: Python :: 3.6
Requires: pytest
Requires-Dist: redis
